odoo/addons/somconnexio/.gitignore
odoo/addons/somconnexio/CHANGELOG.md
odoo/addons/somconnexio/README.md
odoo/addons/somconnexio/__init__.py
odoo/addons/somconnexio/__manifest__.py
odoo/addons/somconnexio/hooks.py
odoo/addons/somconnexio/controllers/__init__.py
odoo/addons/somconnexio/controllers/controllers.py
odoo/addons/somconnexio/controllers/http.py
odoo/addons/somconnexio/controllers/public_controller.py
odoo/addons/somconnexio/correos_services/__init__.py
odoo/addons/somconnexio/correos_services/shipment.py
odoo/addons/somconnexio/crons/activate_change_tariff_OTRS_tickets_cron.xml
odoo/addons/somconnexio/crons/contract_compute_current_tariff_cron.xml
odoo/addons/somconnexio/crons/crm_track_correos_delivery_cron.xml
odoo/addons/somconnexio/data/account.account.template-sc.csv
odoo/addons/somconnexio/data/account_chart_template_data.xml
odoo/addons/somconnexio/data/account_group.xml
odoo/addons/somconnexio/data/account_journal.xml
odoo/addons/somconnexio/data/account_payment_mode.xml
odoo/addons/somconnexio/data/account_payment_term.xml
odoo/addons/somconnexio/data/account_tax.xml
odoo/addons/somconnexio/data/account_tax_group.xml
odoo/addons/somconnexio/data/analytic_account.xml
odoo/addons/somconnexio/data/base_automation.xml
odoo/addons/somconnexio/data/company.xml
odoo/addons/somconnexio/data/contract_group.xml
odoo/addons/somconnexio/data/contract_terminate_reason.xml
odoo/addons/somconnexio/data/contract_terminate_user_reason.xml
odoo/addons/somconnexio/data/crm_categories.xml
odoo/addons/somconnexio/data/crm_stage_data.xml
odoo/addons/somconnexio/data/crm_team.xml
odoo/addons/somconnexio/data/discovery_channel.xml
odoo/addons/somconnexio/data/fiber_signal_type_data.xml
odoo/addons/somconnexio/data/hr_attendance_place.xml
odoo/addons/somconnexio/data/ir_config_pararameter.xml
odoo/addons/somconnexio/data/ir_sequence.xml
odoo/addons/somconnexio/data/mail_activity_type.xml
odoo/addons/somconnexio/data/mail_data.xml
odoo12_addon_somconnexio-12.0.2.13.3.dist-info/METADATA
odoo12_addon_somconnexio-12.0.2.13.3.dist-info/WHEEL
odoo12_addon_somconnexio-12.0.2.13.3.dist-info/top_level.txt
odoo12_addon_somconnexio-12.0.2.13.3.dist-info/RECORD
