Metadata-Version: 2.1
Name: odoo12-addon-somconnexio
Version: 12.0.2.13.3
Summary: Odoo Som Connexió customizations
Home-page: https://coopdevs.org
Author: Coopdevs Treball SCCL, Som Connexió SCCL
License: AGPL-3
Platform: UNKNOWN
Classifier: Programming Language :: Python
Classifier: Framework :: Odoo
Classifier: Framework :: Odoo :: 12.0
Classifier: License :: OSI Approved :: GNU Affero General Public License v3
Requires-Python: >=3.5
Requires-Dist: correos-preregistro (==0.0.6)
Requires-Dist: correos-seguimiento (==0.3.0)
Requires-Dist: factory-boy
Requires-Dist: faker (==9.3.1)
Requires-Dist: hashids (==1.3.1)
Requires-Dist: mm-proxy-python-client (==0.1.0)
Requires-Dist: odoo12-addon-account-asset-management (==12.0.3.1.5)
Requires-Dist: odoo12-addon-account-banking-sepa-credit-transfer (==12.0.1.0.0.99.dev11)
Requires-Dist: odoo12-addon-account-banking-sepa-direct-debit (==12.0.1.3.0)
Requires-Dist: odoo12-addon-account-chart-update (==12.0.1.0.2.99.dev7)
Requires-Dist: odoo12-addon-account-due-list (==12.0.1.0.0.99.dev9)
Requires-Dist: odoo12-addon-account-financial-report (==12.0.1.4.2.99.dev1)
Requires-Dist: odoo12-addon-account-invoice-validation-queued (==12.0.1.0.0.99.dev3)
Requires-Dist: odoo12-addon-account-move-payroll-import (==12.0.1.1.2)
Requires-Dist: odoo12-addon-account-payment-mode (==12.0.1.0.1)
Requires-Dist: odoo12-addon-account-payment-order (==12.0.1.6.3)
Requires-Dist: odoo12-addon-account-payment-partner (==12.0.1.0.2)
Requires-Dist: odoo12-addon-account-payment-return (==12.0.2.1.0)
Requires-Dist: odoo12-addon-account-payment-return-import
Requires-Dist: odoo12-addon-account-payment-return-import-iso20022
Requires-Dist: odoo12-addon-auth-oidc (==12.0.1.1.0)
Requires-Dist: odoo12-addon-base-import-async (==12.0.1.0.0.99.dev10)
Requires-Dist: odoo12-addon-base-rest
Requires-Dist: odoo12-addon-check-concurrent-update (==12.0.1.0.0)
Requires-Dist: odoo12-addon-component-event (==12.0.1.0.0.99.dev11)
Requires-Dist: odoo12-addon-contract-group (==12.0.0.0.0)
Requires-Dist: odoo12-addon-contract-mandate (==12.0.1.0.2)
Requires-Dist: odoo12-addon-contract-payment-mode (==12.0.1.1.0.99.dev4)
Requires-Dist: odoo12-addon-contract (==12.0.7.3.4)
Requires-Dist: odoo12-addon-crm-lead-product (==12.0.1.0.0.99.dev12)
Requires-Dist: odoo12-addon-disable-login (==12.0.1.1.1)
Requires-Dist: odoo12-addon-easy-my-coop-api (==12.0.0.0.1.99.dev22)
Requires-Dist: odoo12-addon-easy-my-coop-es (==12.0.0.0.14)
Requires-Dist: odoo12-addon-easy-my-coop-sponsorship (==12.0.0.0.2)
Requires-Dist: odoo12-addon-easy-my-coop (==12.0.3.0.2.99.dev2)
Requires-Dist: odoo12-addon-hr-attendance-report-theoretical-time (==12.0.1.5.1)
Requires-Dist: odoo12-addon-hr-holidays-public (==12.0.1.1.1.99.dev3)
Requires-Dist: odoo12-addon-hr-holidays-leave-auto-approve
Requires-Dist: odoo12-addon-l10n-es-account-asset (==12.0.2.0.6)
Requires-Dist: odoo12-addon-l10n-es-account-bank-statement-import-n43 (==12.0.1.0.6)
Requires-Dist: odoo12-addon-l10n-es-aeat-mod111 (==12.0.1.4.0.99.dev1)
Requires-Dist: odoo12-addon-l10n-es-aeat-mod190 (==12.0.1.0.2)
Requires-Dist: odoo12-addon-l10n-es-aeat-mod303 (==12.0.3.2.0.99.dev1)
Requires-Dist: odoo12-addon-l10n-es-aeat-mod347 (==12.0.2.0.0.99.dev2)
Requires-Dist: odoo12-addon-l10n-es-aeat-mod349 (==12.0.1.3.4)
Requires-Dist: odoo12-addon-l10n-es-aeat-mod390 (==12.0.3.1.0)
Requires-Dist: odoo12-addon-l10n-es-aeat (==12.0.2.3.1)
Requires-Dist: odoo12-addon-l10n-es-mis-report (==12.0.1.1.0)
Requires-Dist: odoo12-addon-l10n-es-partner (==12.0.1.0.2)
Requires-Dist: odoo12-addon-l10n-es-toponyms (==12.0.1.0.0.99.dev9)
Requires-Dist: odoo12-addon-mail-activity-board (==12.0.1.0.1)
Requires-Dist: odoo12-addon-mail-activity-done (==12.0.1.1.0)
Requires-Dist: odoo12-addon-mass-editing (==12.0.2.2.0)
Requires-Dist: odoo12-addon-mass-mailing-list-dynamic (==12.0.1.0.3)
Requires-Dist: odoo12-addon-mis-builder-budget (==12.0.3.5.0)
Requires-Dist: odoo12-addon-mis-builder (==12.0.3.6.4)
Requires-Dist: odoo12-addon-partner-firstname (==12.0.1.1.0)
Requires-Dist: odoo12-addon-partner-priority (==12.0.1.0.0.99.dev3)
Requires-Dist: odoo12-addon-product-pack (==12.0.1.0.1.99.dev5)
Requires-Dist: odoo12-addon-queue-job (==12.0.1.5.0)
Requires-Dist: odoo12-addon-server-environment (==12.0.2.0.4)
Requires-Dist: odoo12-addon-web-decimal-numpad-dot (==12.0.1.0.0.99.dev9)
Requires-Dist: odoo12-addon-web-favicon (==12.0.1.0.0.99.dev14)
Requires-Dist: odoo12-addon-web-no-bubble (==12.0.1.0.0.99.dev8)
Requires-Dist: odoo12-addon-web-responsive (==12.0.2.3.2)
Requires-Dist: odoo12-addon-web-searchbar-full-width (==12.0.1.0.0.99.dev6)
Requires-Dist: odoo12-addon-web-widget-open-tab (==12.0.1.0.1.99.dev2)
Requires-Dist: odoo12-addon-web-m2x-options
Requires-Dist: odoo (<12.1dev,>=12.0a)
Requires-Dist: openupgradelib (==3.6.1)
Requires-Dist: otrs-somconnexio (==0.6.2)
Requires-Dist: pyopencell (==0.4.9)
Requires-Dist: python-stdnum (==1.14)
